Metadata-Version: 1.1
Name: middleware
Version: 1.2.2
Summary: Python module to add general middleware
Home-page: https://github.com/davidbetz/middleware
Author: David Betz
Author-email: dfb@davidbetz.net
License: UNKNOWN
Keywords: middleware
Platform: UNKNOWN
Classifier: Intended Audience :: Developers
Classifier: Topic :: Software Development :: Build Tools
Classifier: License :: OSI Approved :: MIT License
Classifier: Programming Language :: Python :: 2.7
Classifier: Programming Language :: Python :: 3.6
